docassemble-stubs/docassemble.pyi
docassemble-stubs/base/DA.pyi
docassemble-stubs/base/__init__.pyi
docassemble-stubs/base/actions.pyi
docassemble-stubs/base/amazon.pyi
docassemble-stubs/base/astparser.pyi
docassemble-stubs/base/bates.pyi
docassemble-stubs/base/config.pyi
docassemble-stubs/base/core.pyi
docassemble-stubs/base/error.pyi
docassemble-stubs/base/file_docx.pyi
docassemble-stubs/base/filter.pyi
docassemble-stubs/base/functions.pyi
docassemble-stubs/base/generate_key.pyi
docassemble-stubs/base/geocode.pyi
docassemble-stubs/base/interview_cache.pyi
docassemble-stubs/base/legal.pyi
docassemble-stubs/base/logger.pyi
docassemble-stubs/base/mako.pyi
docassemble-stubs/base/marisol.pyi
docassemble-stubs/base/mermaid.pyi
docassemble-stubs/base/microsoft.pyi
docassemble-stubs/base/pandoc.pyi
docassemble-stubs/base/parse.pyi
docassemble-stubs/base/pdfa.pyi
docassemble-stubs/base/pdftk.pyi
docassemble-stubs/base/read_config.pyi
docassemble-stubs/base/rtfng.pyi
docassemble-stubs/base/sql.pyi
docassemble-stubs/base/standardformatter.pyi
docassemble-stubs/base/test.pyi
docassemble-stubs/base/util.pyi
docassemble-stubs/base/mako/__init__.pyi
docassemble-stubs/base/mako/_ast_util.pyi
docassemble-stubs/base/mako/ast.pyi
docassemble-stubs/base/mako/cache.pyi
docassemble-stubs/base/mako/cmd.pyi
docassemble-stubs/base/mako/codegen.pyi
docassemble-stubs/base/mako/compat.pyi
docassemble-stubs/base/mako/exceptions.pyi
docassemble-stubs/base/mako/ext.pyi
docassemble-stubs/base/mako/filters.pyi
docassemble-stubs/base/mako/lexer.pyi
docassemble-stubs/base/mako/lookup.pyi
docassemble-stubs/base/mako/parsetree.pyi
docassemble-stubs/base/mako/pygen.pyi
docassemble-stubs/base/mako/pyparser.pyi
docassemble-stubs/base/mako/runtime.pyi
docassemble-stubs/base/mako/template.pyi
docassemble-stubs/base/mako/util.pyi
docassemble-stubs/base/mako/ext/__init__.pyi
docassemble-stubs/base/mako/ext/autohandler.pyi
docassemble-stubs/base/mako/ext/babelplugin.pyi
docassemble_stubs-1.4.72b1.dist-info/LICENSE
docassemble_stubs-1.4.72b1.dist-info/METADATA
docassemble_stubs-1.4.72b1.dist-info/WHEEL
docassemble_stubs-1.4.72b1.dist-info/top_level.txt
docassemble_stubs-1.4.72b1.dist-info/RECORD
