Metadata-Version: 2.1
Name: docassemble-stubs
Version: 1.4.72b1
Author: Bryce Willey
License-File: LICENSE
Requires-Dist: docassemble.base ==1.4.72
Requires-Dist: types-Pygments
